PyQt5/bindings/PyQtAds/DockAreaTabBar.sip
PyQt5/bindings/PyQtAds/DockAreaTitleBar.sip
PyQt5/bindings/PyQtAds/DockAreaTitleBar_p.sip
PyQt5/bindings/PyQtAds/DockAreaWidget.sip
PyQt5/bindings/PyQtAds/DockComponentsFactory.sip
PyQt5/bindings/PyQtAds/DockContainerWidget.sip
PyQt5/bindings/PyQtAds/DockFocusController.sip
PyQt5/bindings/PyQtAds/DockManager.sip
PyQt5/bindings/PyQtAds/DockOverlay.sip
PyQt5/bindings/PyQtAds/DockSplitter.sip
PyQt5/bindings/PyQtAds/DockWidget.sip
PyQt5/bindings/PyQtAds/DockWidgetTab.sip
PyQt5/bindings/PyQtAds/DockingStateReader.sip
PyQt5/bindings/PyQtAds/ElidingLabel.sip
PyQt5/bindings/PyQtAds/FloatingDockContainer.sip
PyQt5/bindings/PyQtAds/FloatingDragPreview.sip
PyQt5/bindings/PyQtAds/IconProvider.sip
PyQt5/bindings/PyQtAds/PyQtAds.toml
PyQt5/bindings/PyQtAds/ads.sip
PyQt5/bindings/PyQtAds/ads_globals.sip
PyQtAds.pyd
PyQtAds-3.8.1.dist-info/WHEEL
PyQtAds-3.8.1.dist-info/METADATA
PyQtAds-3.8.1.dist-info/RECORD
