Metadata-Version: 2.1
Name: PyQtAds
Version: 3.8.1
Requires-Python: >=3.6
Summary: Python bindings for Qt Advanced Docking System
Home-Page: https://github.com/githubuser0xFFFF/Qt-Advanced-Docking-System/
License: LGPL v2.1
Requires-Dist: PyQt5-sip (>=12.8, <13)
Requires-Dist: PyQt5 (>=5.15.4)
